dbt/__init__.py
dbt/adapters/buenavista/__init__.py
dbt/adapters/buenavista/credentials.py
dbt/adapters/buenavista/python_extension.py
dbt/adapters/buenavista/python_job.py
dbt/adapters/bv_duckdb/__init__.py
dbt/adapters/bv_duckdb/__version__.py
dbt/adapters/bv_duckdb/connections.py
dbt/adapters/bv_duckdb/impl.py
dbt/adapters/bv_postgres/__init__.py
dbt/adapters/bv_postgres/__version__.py
dbt/adapters/bv_postgres/connections.py
dbt/adapters/bv_postgres/impl.py
dbt/include/bv_duckdb/__init__.py
dbt/include/bv_duckdb/dbt_project.yml
dbt/include/bv_duckdb/macros/adapter.sql
dbt/include/bv_postgres/__init__.py
dbt/include/bv_postgres/dbt_project.yml
dbt/include/bv_postgres/macros/adapter.sql
dbt/include/bv_postgres/macros/materializations/table.sql
dbt_buenavista-1.3.0.dist-info/LICENSE
dbt_buenavista-1.3.0.dist-info/METADATA
dbt_buenavista-1.3.0.dist-info/WHEEL
dbt_buenavista-1.3.0.dist-info/top_level.txt
dbt_buenavista-1.3.0.dist-info/RECORD
