Metadata-Version: 2.1
Name: dbt-buenavista
Version: 1.3.0
Summary: The buenavista adapter plugin for dbt (data build tool)
Home-page: https://github.com/jwills/dbt-buenavista
Author: Josh Wills
Author-email: joshwills+dbt@gmail.com
License-File: LICENSE
Requires-Dist: dbt-postgres (~=1.3.0)
Provides-Extra: duckdb
Requires-Dist: dbt-duckdb (~=1.3.0) ; extra == 'duckdb'
